__init__.py
iso6709/__init__.py
iso6709/iso6709.py
iso6709-0.1.5.data/data/CHANGELOG.rst
iso6709-0.1.5.dist-info/METADATA
iso6709-0.1.5.dist-info/WHEEL
iso6709-0.1.5.dist-info/top_level.txt
iso6709-0.1.5.dist-info/RECORD
